calender/__init__.py
calender/admin.py
calender/apps.py
calender/context_processors.py
calender/forms.py
calender/migrations/0001_initial.py
calender/migrations/0002_alter_register_is_present.py
calender/migrations/__init__.py
calender/models.py
calender/templates/calender/register_form.html
calender/urls.py
calender/views.py
films/__init__.py
films/admin.py
films/apps.py
films/clients/__init__.py
films/clients/imdb.py
films/clients/omdb.py
films/core/__init__.py
films/core/types.py
films/forms.py
films/migrations/0001_initial.py
films/migrations/0002_auto_20191102_1705.py
films/migrations/0003_auto_20191102_1838.py
films/migrations/0004_film_poster_url.py
films/migrations/0005_film_genre.py
films/migrations/0006_auto_20191103_1609.py
films/migrations/0007_auto_20191116_2302.py
films/migrations/0008_film_bbfc_age.py
films/migrations/0009_auto_20200322_1602.py
films/migrations/0010_auto_20200322_2242.py
films/migrations/0011_auto_20200322_2311.py
films/migrations/0012_auto_20210605_1155.py
films/migrations/__init__.py
films/models.py
films/templates/films/film_form.html
films/templatetags/__init__.py
films/templatetags/films_extras.py
films/urls.py
films/views.py
manage.py
schedule/__init__.py
schedule/apps.py
schedule/logic.py
schedule/migrations/__init__.py
schedule/templates/schedule/schedule.html
schedule/urls.py
schedule/views.py
vote4film/__init__.py
vote4film/auth.py
vote4film/log.py
vote4film/middleware.py
vote4film/settings.py
vote4film/urls.py
vote4film/wsgi.py
votes/__init__.py
votes/admin.py
votes/apps.py
votes/context_processors.py
votes/forms.py
votes/logic.py
votes/migrations/0001_initial.py
votes/migrations/0002_auto_20191103_1609.py
votes/migrations/__init__.py
votes/models.py
votes/templates/votes/includes/film_card.html
votes/templates/votes/vote_aggregate.html
votes/templates/votes/vote_form.html
votes/urls.py
votes/views.py
web/__init__.py
web/static/web/favicon/README.txt
web/static/web/favicon/apple-touch-icon.png
vote4film-1.7.5.dist-info/entry_points.txt
vote4film-1.7.5.dist-info/LICENSE
vote4film-1.7.5.dist-info/WHEEL
vote4film-1.7.5.dist-info/METADATA
vote4film-1.7.5.dist-info/RECORD
