Metadata-Version: 2.1
Name: vote4film
Version: 1.7.5
Summary: Easy scheduling for regular film nights
Home-page: https://github.com/Fustra/vote4film/
License: AGPL-3.0
Author: QasimK
Author-email: noreply@QasimK.io
Requires-Python: >=3.8,<4.0
Classifier: Development Status :: 3 - Alpha
Classifier: Environment :: No Input/Output (Daemon)
Classifier: License :: OSI Approved :: GNU Affero General Public License v3
Classifier: Natural Language :: English
Classifier: Operating System :: OS Independent
Classifier: Programming Language :: Python :: 3
Classifier: Programming Language :: Python :: 3.10
Classifier: Programming Language :: Python :: 3.8
Classifier: Programming Language :: Python :: 3.9
Classifier: Topic :: Internet :: WWW/HTTP :: WSGI :: Application
Provides-Extra: postgres
Provides-Extra: sentry
Requires-Dist: bbfcapi (>=3.0.1,<4.0.0)
Requires-Dist: django (>=3.2,<4.0)
Requires-Dist: django-environ (>=0.8.1,<0.9.0)
Requires-Dist: django-extensions (>=3.1.3,<4.0.0)
Requires-Dist: lxml (>=4.6.3,<5.0.0)
Requires-Dist: psycopg2 (>=2.8.6,<3.0.0); extra == "postgres"
Requires-Dist: pyhumps (>=3.0.2,<4.0.0)
Requires-Dist: requests (>=2.25.1,<3.0.0)
Requires-Dist: sentry-sdk (>=1.1,<2.0); extra == "sentry"
Requires-Dist: xdg (>=5.0.2,<6.0.0)
Project-URL: Repository, https://github.com/Fustra/vote4film/
